simple_tracker/__init__.py
simple_tracker/models.py
simple_tracker-0.1.3.dist-info/LICENSE
simple_tracker-0.1.3.dist-info/METADATA
simple_tracker-0.1.3.dist-info/WHEEL
simple_tracker-0.1.3.dist-info/top_level.txt
simple_tracker-0.1.3.dist-info/RECORD
