Metadata-Version: 2.1
Name: simple-tracker
Version: 0.1.3
Summary: Track multiple objects using just x, y coordinates
Home-page: https://github.com/bherbruck/simple_tracker
Author: Brennen Herbruck
Author-email: brennen.hrbruck@gmail.com
License: UNKNOWN
Platform: UNKNOWN
Classifier: Programming Language :: Python :: 3
Classifier: License :: OSI Approved :: MIT License
Classifier: Operating System :: OS Independent
Requires-Python: >=3.6
